peony/__init__.py
peony/backup.py
peony/caddy.py
peony/caddy_settings
peony/docker_manager.py
peony/utils.py
peony/vpn.py
peony/vpn_settings
peony/templates/caddy/Caddyfile
peony/templates/caddy/docker-compose.yaml
peony/templates/caddy/vpn-select.html
peony/templates/vpns/client.conf
peony/templates/vpns/docker-compose.yml
peony/templates/vpns/easy-rsa.vars
peony/templates/vpns/server.conf
peonyvpn-0.1.1.dist-info/METADATA
peonyvpn-0.1.1.dist-info/WHEEL
peonyvpn-0.1.1.dist-info/entry_points.txt
peonyvpn-0.1.1.dist-info/top_level.txt
peonyvpn-0.1.1.dist-info/RECORD
