Metadata-Version: 2.1
Name: peonyvpn
Version: 0.1.1
Summary: A VPN management tool
Author-email: flog <florian.grave@epitech.eu>
License: MIT
Requires-Python: >=3.8
Requires-Dist: docker>=6.1.0
